enniolearning/__init__.py
enniolearning/ennio_midi_model.py
enniolearning/ennio_models_evaluation.py
enniolearning/ennio_prediction.py
enniolearning/ennio_pretraining.py
enniolearning/ennio_train_and_evaluate.py
enniolearning/ennio_training.py
enniolearning/eta_tools.py
enniolearning/prediction_fcts.py
enniolearning/training_fcts.py
enniolearning/utils.py
enniolearning/test/__init__.py
enniolearning/test/test_cuda.py
enniolearning-0.2.0.dist-info/LICENSE.txt
enniolearning-0.2.0.dist-info/METADATA
enniolearning-0.2.0.dist-info/WHEEL
enniolearning-0.2.0.dist-info/top_level.txt
enniolearning-0.2.0.dist-info/RECORD
