Metadata-Version: 2.1
Name: enniolearning
Version: 0.2.0
Summary: A Machine Learning engine for MID music files, based on PyTorch framework.
Home-page: https://github.com/Mara-tech/Ennio-Learning
Author: Pierrick Baudet
Author-email: pbaudet.enseirb@gmail.com
License: see LICENSE.txt
Platform: UNKNOWN
Requires-Dist: music21 (>=6.1.0)
Requires-Dist: torch (>=1.6.0)
Requires-Dist: numpy
Requires-Dist: pandas
Requires-Dist: matplotlib
Requires-Dist: jordan-py (>=1.0.0)
